[
  {
    "id": 0,
    "label_up_1": "Tammikuu",
    "label_up_2": "Tammikuu",
    "label_up_3": "Tammikuu",
    "label_up_4": "Tammikuu",
    "label_up_5": "Tammikuu",
    "label_up_6": "Tammikuu",
    "label_down_1": "AVOIMIA PAIKKOJA",
    "label_down_2": "TYÖJONOSSA",
    "label_down_3": "Tammikuu",
    "label_down_4": "Tammikuu",
    "label_down_5": "Tammikuu",
    "label_down_6": "Tammikuu",
    "value_up_1": "99",
    "value_up_2": "9",
    "value_up_3": "Tammikuu",
    "value_up_4": "Tammikuu",
    "value_up_5": "Tammikuu",
    "value_up_6": "Tammikuu",
    "value_down_1": "Paikka ihan tosi\nPaikka2\nTULOSSA:\nPaikka4\nJoojoo\nAijaaniinpitkä\n",
    "value_down_2": "Tammikuu\nkukkuu\njaajaa\nniin",
    "value_down_3": "Tammikuu",
    "value_down_4": "Tammikuu",
    "value_down_5": "Tammikuu",
    "value_down_6": "Tammikuu",
    "label_right_down_1": "Puh. haastattelu",
    "value_right_down_1": "15",
    "label_right_down_2": "Live-haastattelu",
    "value_right_down_2": "7",
    "update_info": "Päivitetty 29.1.2018"
  },
  {
    "id": 1,
    "label_up_1": "Tammikuu",
    "label_up_2": "Tammikuu",
    "label_up_3": "Tammikuu",
    "label_up_4": "Tammikuu",
    "label_up_5": "Tammikuu",
    "label_up_6": "Tammikuu",
    "label_down_1": "AVOIMIA PAIKKOJA",
    "label_down_2": "TYÖJONOSSA",
    "label_down_3": "Tammikuu",
    "label_down_4": "Tammikuu",
    "label_down_5": "Tammikuu",
    "label_down_6": "Tammikuu",
    "value_up_1": "99",
    "value_up_2": "8",
    "value_up_3": "Tammikuu",
    "value_up_4": "Tammikuu",
    "value_up_5": "Tammikuu",
    "value_up_6": "Tammikuu",
    "value_down_1": "Paikka ihan tosi\nPaikka2\nTULOSSA:\nPaikka4\nJoojoo\nAijaaniinpitkä\n",
    "value_down_2": "Tammikuu",
    "value_down_3": "Tammikuu",
    "value_down_4": "Tammikuu",
    "value_down_5": "Tammikuu",
    "value_down_6": "Tammikuu",
    "label_right_down_1": "Roadmap",
    "value_right_down_1": "5",
    "label_right_down_2": "Neuvottelu",
    "value_right_down_2": "3",
    "update_info": "Päivitetty 29.1.2018"
  },
  {
    "id": 2,
    "label_up_1": "Tammikuu",
    "label_up_2": "Helmikuu",
    "label_up_3": "Maaliskuu",
    "label_up_4": "Huhtikuu",
    "label_up_5": "Toukokuu",
    "label_up_6": "Kesäkuu",
    "label_down_1": "Heinäkuu",
    "label_down_2": "Elokuu",
    "label_down_3": "Syyskuu",
    "label_down_4": "Lokakuu",
    "label_down_5": "Marraskuu",
    "label_down_6": "Joulukuu",
    "value_up_1": "99",
    "value_up_2": "8",
    "value_up_3": "Tammikuu",
    "value_up_4": "Tammikuu",
    "value_up_5": "Tammikuu",
    "value_up_6": "Tammikuu",
    "value_down_1": "Paikka ihan tosi\nPaikka2\nTULOSSA:\nPaikka4\nJoojoo\nAijaaniinpitkä\n",
    "value_down_2": "Tammikuu",
    "value_down_3": "Tammikuu",
    "value_down_4": "Tammikuu",
    "value_down_5": "Tammikuu",
    "value_down_6": "Tammikuu",
    "label_right_down_1": "Roadmap",
    "value_right_down_1": "5",
    "label_right_down_2": "Neuvottelu",
    "value_right_down_2": "3",
    "update_info": "Päivitetty 29.1.2018"
  },
  {
    "id": 3,
    "label_up_1": "Tammikuu",
    "label_up_2": "Helmikuu",
    "label_up_3": "Maaliskuu",
    "label_up_4": "Tammikuu",
    "label_up_5": "Tammikuu",
    "label_up_6": "Tammikuu",
    "label_down_1": "AVOIMIA PAIKKOJA",
    "label_down_2": "TYÖJONOSSA",
    "label_down_3": "Tammikuu",
    "label_down_4": "Tammikuu",
    "label_down_5": "Tammikuu",
    "label_down_6": "Tammikuu",
    "value_up_1": "99",
    "value_up_2": "8",
    "value_up_3": "Tammikuu",
    "value_up_4": "Tammikuu",
    "value_up_5": "Tammikuu",
    "value_up_6": "Tammikuu",
    "value_down_1": "Paikka ihan tosi\nPaikka2\nTULOSSA:\nPaikka4\nJoojoo\nAijaaniinpitkä\n",
    "value_down_2": "Tammikuu",
    "value_down_3": "Tammikuu",
    "value_down_4": "Tammikuu",
    "value_down_5": "Tammikuu",
    "value_down_6": "Tammikuu",
    "label_right_down_1": "Roadmap",
    "value_right_down_1": "5",
    "label_right_down_2": "Neuvottelu",
    "value_right_down_2": "3",
    "update_info": "Päivitetty 29.1.2018"
  }
]